README.md
setup.py
theogravity_pulumi_fusionauth/__init__.py
theogravity_pulumi_fusionauth/_inputs.py
theogravity_pulumi_fusionauth/_utilities.py
theogravity_pulumi_fusionauth/fusion_auth_api_key.py
theogravity_pulumi_fusionauth/fusion_auth_application.py
theogravity_pulumi_fusionauth/fusion_auth_application_role.py
theogravity_pulumi_fusionauth/fusion_auth_e_mail.py
theogravity_pulumi_fusionauth/fusion_auth_entity.py
theogravity_pulumi_fusionauth/fusion_auth_entity_grant.py
theogravity_pulumi_fusionauth/fusion_auth_entity_type.py
theogravity_pulumi_fusionauth/fusion_auth_entity_type_permission.py
theogravity_pulumi_fusionauth/fusion_auth_form.py
theogravity_pulumi_fusionauth/fusion_auth_form_field.py
theogravity_pulumi_fusionauth/fusion_auth_generic_connector.py
theogravity_pulumi_fusionauth/fusion_auth_group.py
theogravity_pulumi_fusionauth/fusion_auth_idp_apple.py
theogravity_pulumi_fusionauth/fusion_auth_idp_external_jwt.py
theogravity_pulumi_fusionauth/fusion_auth_idp_facebook.py
theogravity_pulumi_fusionauth/fusion_auth_idp_google.py
theogravity_pulumi_fusionauth/fusion_auth_idp_linked_in.py
theogravity_pulumi_fusionauth/fusion_auth_idp_open_id_connect.py
theogravity_pulumi_fusionauth/fusion_auth_idp_psn.py
theogravity_pulumi_fusionauth/fusion_auth_idp_saml_v2_idp_initiated.py
theogravity_pulumi_fusionauth/fusion_auth_idp_samlv2.py
theogravity_pulumi_fusionauth/fusion_auth_idp_steam.py
theogravity_pulumi_fusionauth/fusion_auth_idp_twitch.py
theogravity_pulumi_fusionauth/fusion_auth_idp_x_box.py
theogravity_pulumi_fusionauth/fusion_auth_imported_key.py
theogravity_pulumi_fusionauth/fusion_auth_key.py
theogravity_pulumi_fusionauth/fusion_auth_lambda.py
theogravity_pulumi_fusionauth/fusion_auth_reactor.py
theogravity_pulumi_fusionauth/fusion_auth_registration.py
theogravity_pulumi_fusionauth/fusion_auth_system_configuration.py
theogravity_pulumi_fusionauth/fusion_auth_tenant.py
theogravity_pulumi_fusionauth/fusion_auth_theme.py
theogravity_pulumi_fusionauth.egg-info/PKG-INFO
theogravity_pulumi_fusionauth.egg-info/SOURCES.txt
theogravity_pulumi_fusionauth.egg-info/dependency_links.txt
theogravity_pulumi_fusionauth.egg-info/not-zip-safe
theogravity_pulumi_fusionauth.egg-info/requires.txt
theogravity_pulumi_fusionauth.egg-info/top_level.txt
