Metadata-Version: 2.1
Name: theogravity-pulumi-fusionauth
Version: 5.1.0
Summary: A Pulumi package for managing FusionAuth instances.
Home-page: https://github.com/theogravity/pulumi-fusionauth
License: MIT
Project-URL: Repository, https://github.com/theogravity/pulumi-fusionauth
Keywords: pulumi fusionauth category/infrastructure
Platform: UNKNOWN
Requires-Python: >=3.8
